odoo9_addon_purchase_request_to_requisition-9.0.1.0.0-py2.7-nspkg.pth
odoo_addons/purchase_request_to_requisition/__openerp__.py
odoo_addons/purchase_request_to_requisition/__init__.py
odoo_addons/purchase_request_to_requisition/README.rst
odoo_addons/purchase_request_to_requisition/security/ir.model.access.csv
odoo_addons/purchase_request_to_requisition/models/product.py
odoo_addons/purchase_request_to_requisition/models/purchase_requisition.py
odoo_addons/purchase_request_to_requisition/models/__init__.py
odoo_addons/purchase_request_to_requisition/models/purchase_request.py
odoo_addons/purchase_request_to_requisition/i18n/it.po
odoo_addons/purchase_request_to_requisition/i18n/es.po
odoo_addons/purchase_request_to_requisition/i18n/fr_FR.po
odoo_addons/purchase_request_to_requisition/i18n/sl.po
odoo_addons/purchase_request_to_requisition/i18n/de.po
odoo_addons/purchase_request_to_requisition/i18n/fr.po
odoo_addons/purchase_request_to_requisition/i18n/pt_BR.po
odoo_addons/purchase_request_to_requisition/wizard/purchase_request_line_make_purchase_requisition_view.xml
odoo_addons/purchase_request_to_requisition/wizard/purchase_request_line_make_purchase_requisition.py
odoo_addons/purchase_request_to_requisition/wizard/__init__.py
odoo_addons/purchase_request_to_requisition/views/purchase_request_view.xml
odoo_addons/purchase_request_to_requisition/views/purchase_requisition_view.xml
odoo_addons/purchase_request_to_requisition/tests/test_purchase_request_to_requisition.py
odoo_addons/purchase_request_to_requisition/tests/__init__.py
odoo_addons/purchase_request_to_requisition/static/description/icon.png
odoo9_addon_purchase_request_to_requisition-9.0.1.0.0.dist-info/top_level.txt
odoo9_addon_purchase_request_to_requisition-9.0.1.0.0.dist-info/WHEEL
odoo9_addon_purchase_request_to_requisition-9.0.1.0.0.dist-info/RECORD
odoo9_addon_purchase_request_to_requisition-9.0.1.0.0.dist-info/metadata.json
odoo9_addon_purchase_request_to_requisition-9.0.1.0.0.dist-info/DESCRIPTION.rst
odoo9_addon_purchase_request_to_requisition-9.0.1.0.0.dist-info/METADATA
odoo9_addon_purchase_request_to_requisition-9.0.1.0.0.dist-info/namespace_packages.txt
