Metadata-Version: 2.0
Name: odoo9-addon-purchase-request-to-requisition
Version: 9.0.1.0.0
Summary: Purchase Request to Call for Bids
Home-page: https://github.com/OCA/purchase-workflow
Author: Eficent, Acsone SA/NV,Odoo Community Association (OCA)
Author-email: support@odoo-community.org
License: LGPL-3
Platform: UNKNOWN
Requires-Dist: odoo (<9.1a,>=9.0a)
Requires-Dist: odoo9-addon-purchase-request-procurement
Requires-Dist: odoo9-addon-purchase-request-to-rfq
Classifier: Programming Language :: Python :: 2.7
Classifier: Framework :: Odoo
Classifier: License :: OSI Approved :: GNU Lesser General Public License v3 (LGPLv3)
